ironswarm/__about__.py
ironswarm/__init__.py
ironswarm/context.py
ironswarm/helper.py
ironswarm/logging_config.py
ironswarm/lwwelementset.py
ironswarm/node.py
ironswarm/scenario.py
ironswarm/scenario_manager.py
ironswarm/scheduler.py
ironswarm/serialization.py
ironswarm/types.py
ironswarm/volumemodel.py
ironswarm/datapools/__init__.py
ironswarm/datapools/base_datapool.py
ironswarm/datapools/file_datapool.py
ironswarm/datapools/iterable_datapool.py
ironswarm/datapools/recyclable_datapool.py
ironswarm/datapools/recyclable_file_datapool.py
ironswarm/journey/http.py
ironswarm/journey/log.py
ironswarm/metrics/__init__.py
ironswarm/metrics/collector.py
ironswarm/metrics/events.py
ironswarm/metrics/graphs.py
ironswarm/metrics/report.py
ironswarm/transport/__init__.py
ironswarm/transport/zmq.py
ironswarm-0.0.2.dist-info/METADATA
ironswarm-0.0.2.dist-info/WHEEL
ironswarm-0.0.2.dist-info/entry_points.txt
ironswarm-0.0.2.dist-info/licenses/LICENSE
ironswarm-0.0.2.dist-info/RECORD
