Metadata-Version: 2.4
Name: ironswarm
Version: 0.0.2
Summary: Distributed HTTP load testing framework with journey-based scenarios
Project-URL: Documentation, https://github.com/ryan-h265/ironswarm#readme
Project-URL: Issues, https://github.com/ryan-h265/ironswarm/issues
Project-URL: Source, https://github.com/ryan-h265/ironswarm
Author-email: Ryan <ryan@h265.email>
License-File: LICENSE
Keywords: async,distributed,http,load-testing,performance
Classifier: Development Status :: 4 - Beta
Classifier: Intended Audience :: Developers
Classifier: License :: OSI Approved :: MIT License
Classifier: Programming Language :: Python
Classifier: Programming Language :: Python :: 3.10
Classifier: Programming Language :: Python :: 3.11
Classifier: Programming Language :: Python :: 3.12
Classifier: Programming Language :: Python :: 3.13
Classifier: Programming Language :: Python :: 3.14
Classifier: Programming Language :: Python :: Implementation :: CPython
Classifier: Programming Language :: Python :: Implementation :: PyPy
Classifier: Topic :: Software Development :: Testing
Classifier: Topic :: System :: Distributed Computing
Requires-Python: >=3.10
Requires-Dist: aiohttp>=3.13.0
Requires-Dist: msgpack>=1.0.0
Requires-Dist: pyzmq>=27.1.0
Provides-Extra: graphs
Requires-Dist: matplotlib>=3.10.0; extra == 'graphs'
